listchaining/__init__.py
listchaining/list_methods.py
listchaining/utils.py
listchaining-1.0.10.dist-info/LICENSE
listchaining-1.0.10.dist-info/METADATA
listchaining-1.0.10.dist-info/WHEEL
listchaining-1.0.10.dist-info/top_level.txt
listchaining-1.0.10.dist-info/RECORD
