Metadata-Version: 2.1
Name: listchaining
Version: 1.0.10
Summary: List chaining in Python (from JavaScript arrays)
Home-page: https://github.com/Theodikes/listchaining
Author: Theodike
Author-email: gvedichi@gmail.com
License: UNKNOWN
Keywords: chaining,list chaining,javascript chaining,array chaining
Platform: UNKNOWN
Classifier: Programming Language :: Python
Classifier: Programming Language :: Python :: 3.6
Classifier: Programming Language :: Python :: 3.7
Classifier: Programming Language :: Python :: 3.8
Classifier: Programming Language :: Python :: 3.9
Classifier: Programming Language :: Python :: 3.10
Classifier: Programming Language :: Python :: Implementation :: CPython
Classifier: Programming Language :: Python :: Implementation :: PyPy
Classifier: License :: OSI Approved :: MIT License
Classifier: Operating System :: OS Independent
Requires-Python: >=3.6
License-File: LICENSE
